odoo/addons/sale_product_pack_fixed_discount/README.rst
odoo/addons/sale_product_pack_fixed_discount/__init__.py
odoo/addons/sale_product_pack_fixed_discount/__manifest__.py
odoo/addons/sale_product_pack_fixed_discount/i18n/fr.po
odoo/addons/sale_product_pack_fixed_discount/i18n/it.po
odoo/addons/sale_product_pack_fixed_discount/i18n/sale_product_pack_fixed_discount.pot
odoo/addons/sale_product_pack_fixed_discount/models/__init__.py
odoo/addons/sale_product_pack_fixed_discount/models/sale_order_line.py
odoo/addons/sale_product_pack_fixed_discount/readme/CONTRIBUTORS.md
odoo/addons/sale_product_pack_fixed_discount/readme/DESCRIPTION.md
odoo/addons/sale_product_pack_fixed_discount/readme/ROADMAP.md
odoo/addons/sale_product_pack_fixed_discount/static/description/icon.png
odoo/addons/sale_product_pack_fixed_discount/static/description/index.html
odoo/addons/sale_product_pack_fixed_discount/views/sale_order_views.xml
odoo_addon_sale_product_pack_fixed_discount-17.0.1.0.0.3.dist-info/METADATA
odoo_addon_sale_product_pack_fixed_discount-17.0.1.0.0.3.dist-info/WHEEL
odoo_addon_sale_product_pack_fixed_discount-17.0.1.0.0.3.dist-info/top_level.txt
odoo_addon_sale_product_pack_fixed_discount-17.0.1.0.0.3.dist-info/RECORD
