Metadata-Version: 2.1
Name: odoo-addon-sale_product_pack_fixed_discount
Version: 17.0.1.0.0.3
Requires-Python: >=3.10
Requires-Dist: odoo-addon-sale_fixed_discount>=17.0dev,<17.1dev
Requires-Dist: odoo-addon-sale_product_pack>=17.0dev,<17.1dev
Requires-Dist: odoo>=17.0a,<17.1dev
Summary: Glue module between sale product pack and sale fixed discount
Home-page: https://github.com/OCA/product-pack
License: AGPL-3
Author: Pierre Verkest <pierreverkest84@gmail.com>, Odoo Community Association (OCA),
Author-email: support@odoo-community.org
Classifier: Programming Language :: Python
Classifier: Framework :: Odoo
Classifier: Framework :: Odoo :: 17.0
Classifier: License :: OSI Approved :: GNU Affero General Public License v3
